{
  "total": 1000,
  "decks": {
    "city": 148,
    "tavern": 128,
    "road": 118,
    "forest": 88,
    "dungeon": 88,
    "cave": 68,
    "swamp": 63,
    "mountains": 63,
    "coast": 68,
    "sea": 58,
    "crash": 34,
    "dungeon_finale": 33,
    "special": 43
  },
  "themes": {
    "labor": 50,
    "housing": 50,
    "antifascist": 50,
    "antiwar": 50,
    "anti_genocide": 50,
    "ecology": 55,
    "care": 50,
    "food": 50,
    "colonialism": 50,
    "capital": 50,
    "post_scarcity": 50,
    "liberalism": 50,
    "state_power": 49,
    "union": 49,
    "revolution": 49,
    "freedom": 50,
    "science": 49,
    "faith": 50,
    "propaganda": 49,
    "kindness": 50
  }
}
